{
  "$schema": "https://raw.githubusercontent.com/vedantmgoyal2009/winget-pkgs-automation/main/schema.json",
  "pkgid": "Oracle.VirtualBox",
  "repo_uri": "https://download.virtualbox.org/virtualbox/LATEST.TXT",
  "last_checked_tag": "6.1.30\n",
  "asset_regex": ".*.exe$",
  "is_prerelease": false,
  "version_method": null,
  "use_package_script": true,
  "skip": false,
  "yamlcreate_autoupgrade": false,
  "check_existing_pr": true,
  "previous_timestamp": 1639084896,
  "check_interval": 3600
}
