{
  "$schema": "https://github.com/vedantmgoyal9/winget-pkgs-automation/raw/main/schema.json",
  "PackageIdentifier": "Xmind.Xmind.8",
  "Source": [
    {
      "InvokeType": "RestMethod",
      "Uri": "https://www.xmind.net/_api/checkVersion/0?distrib=cathy_win32",
      "Method": "Get",
      "Headers": {},
      "Body": "",
      "UserAgent": ""
    }
  ],
  "PostResponseScript": "$ReleaseDateRaw = $Response.buildId.Substring($Response.buildId.LastIndexOf('.') + 1, 8)",
  "Update": {
    "PackageVersion": "($Response.buildId | Select-String -Pattern '[0-9.]+').Matches.Value",
    "InstallerUrls": "$Response.download",
    "ReleaseDate": "$ReleaseDateRaw.Substring(0, 4) + '-' + $ReleaseDateRaw.Substring(4, 2) + '-' + $ReleaseDateRaw.Substring(6, 2)",
    "Locales": [
      {
        "Name": "en-us",
        "ReleaseNotes": "$Response.whatsNew"
      }
    ]
  },
  "AdditionalInfo": {
    "ForceUpgrade": false
  },
  "PostUpgradeScript": "",
  "Skip": {
    "Skip?": false,
    "Reason": null
  }
}
